LICENCE.txt
MANIFEST.in
README.rst
setup.cfg
setup.py
diskette/__init__.py
diskette/apps.py
diskette/choices.py
diskette/exceptions.py
diskette/settings.py
diskette/urls.py
diskette.egg-info/PKG-INFO
diskette.egg-info/SOURCES.txt
diskette.egg-info/dependency_links.txt
diskette.egg-info/requires.txt
diskette.egg-info/top_level.txt
diskette.egg-info/zip-safe
diskette/admin/__init__.py
diskette/admin/actions.py
diskette/admin/dump.py
diskette/admin/filters.py
diskette/admin/key.py
diskette/contrib/__init__.py
diskette/contrib/django_configuration.py
diskette/contrib/composer/__init__.py
diskette/contrib/composer/collectors.py
diskette/contrib/composer/processors.py
diskette/core/__init__.py
diskette/core/defaults.py
diskette/core/dumper.py
diskette/core/loader.py
diskette/core/processes.py
diskette/core/storages.py
diskette/core/applications/__init__.py
diskette/core/applications/definitions.py
diskette/core/applications/lookupstore.py
diskette/core/applications/store.py
diskette/core/handlers/__init__.py
diskette/core/handlers/base.py
diskette/core/handlers/dump.py
diskette/core/handlers/load.py
diskette/core/serializers/__init__.py
diskette/core/serializers/dumpdata.py
diskette/core/serializers/loaddata.py
diskette/factories/__init__.py
diskette/factories/dump.py
diskette/factories/key.py
diskette/factories/user.py
diskette/forms/__init__.py
diskette/forms/dump.py
diskette/forms/key.py
diskette/management/__init__.py
diskette/management/commands/__init__.py
diskette/management/commands/diskette_apps.py
diskette/management/commands/diskette_dump.py
diskette/management/commands/diskette_load.py
diskette/management/commands/polymorphic_dumpdata.py
diskette/migrations/0001_initial.py
diskette/migrations/__init__.py
diskette/models/__init__.py
diskette/models/dump.py
diskette/models/key.py
diskette/utils/__init__.py
diskette/utils/filesystem.py
diskette/utils/hashs.py
diskette/utils/http.py
diskette/utils/jsons.py
diskette/utils/lists.py
diskette/utils/loggers.py
diskette/utils/tests.py
diskette/utils/versionning.py
diskette/views/__init__.py
diskette/views/admin_mixins.py
diskette/views/dump.py