Metadata-Version: 2.1
Name: diskette
Version: 0.4.0
Summary: Export and import Django application data and medias
Home-page: https://github.com/emencia/diskette
Author: Emencia
Author-email: support@emencia.com
License: MIT
Project-URL: Source Code, https://github.com/emencia/diskette
Project-URL: Issue Tracker, https://github.com/emencia/diskette/issues
Project-URL: Changelog, https://diskette.readthedocs.io/en/latest/history.html
Project-URL: Documentation, https://diskette.readthedocs.io/
Keywords: Python,Django
Classifier: Development Status :: 5 - Production/Stable
Classifier: Intended Audience :: Developers
Classifier: License :: OSI Approved :: MIT License
Classifier: Natural Language :: English
Classifier: Programming Language :: Python :: 3
Classifier: Programming Language :: Python :: 3.9
Classifier: Programming Language :: Python :: 3.10
Classifier: Programming Language :: Python :: 3.11
Classifier: Framework :: Django
Classifier: Framework :: Django :: 4.0
Classifier: Framework :: Django :: 4.1
Classifier: Framework :: Django :: 4.2
Classifier: Framework :: Django :: 5.0
Classifier: Framework :: Django :: 5.1
Requires-Python: >=3.9
License-File: LICENCE.txt
Requires-Dist: Django>=4.0
Requires-Dist: datalookup>=1.0.0
Requires-Dist: requests>=2.32.3
Requires-Dist: django-sendfile2>=0.7.0
Provides-Extra: dev
Requires-Dist: pytest>=7.0; extra == "dev"
Requires-Dist: pytest-django>=4.5.2; extra == "dev"
Requires-Dist: factory-boy>=3.3.0; extra == "dev"
Requires-Dist: pyquery>=2.0.0; extra == "dev"
Requires-Dist: freezegun>=1.2.0; extra == "dev"
Requires-Dist: requests-mock>=1.10.0; extra == "dev"
Provides-Extra: quality
Requires-Dist: flake8>=6.0.0; extra == "quality"
Requires-Dist: tox>=4.11.0; extra == "quality"
Provides-Extra: doc
Requires-Dist: sphinx>=8.0.2; extra == "doc"
Requires-Dist: furo>=2024.8.6; extra == "doc"
Requires-Dist: sphinx-copybutton>=0.5.2; extra == "doc"
Requires-Dist: tabulate>=0.9.0; extra == "doc"
Requires-Dist: project-composer>=0.7.0; extra == "doc"
Provides-Extra: doc-live
Requires-Dist: livereload>=2.6.0; extra == "doc-live"
Provides-Extra: release
Requires-Dist: twine>=5.0.0; extra == "release"
